clip_score/__init__.py
clip_score/__main__.py
clip_score/clip_score.py
clip_score-0.2.1.dist-info/LICENSE
clip_score-0.2.1.dist-info/METADATA
clip_score-0.2.1.dist-info/WHEEL
clip_score-0.2.1.dist-info/entry_points.txt
clip_score-0.2.1.dist-info/top_level.txt
clip_score-0.2.1.dist-info/RECORD
