Metadata-Version: 2.1
Name: clip-score
Version: 0.2.1
Summary: Package for calculating CLIP-Score using PyTorch
Home-page: https://github.com/taited/clip-score
Author: Taited
Author-email: taited9160@gmail.com
Classifier: Programming Language :: Python :: 3
Classifier: License :: OSI Approved :: Apache Software License
Requires-Python: >=3.5
License-File: LICENSE
Requires-Dist: numpy
Requires-Dist: pillow
Requires-Dist: torch >=1.7.1
Requires-Dist: torchvision >=0.8.2
Requires-Dist: ftfy
Requires-Dist: regex
Requires-Dist: tqdm
Requires-Dist: transformers
Requires-Dist: huggingface-hub
Provides-Extra: dev
Requires-Dist: flake8 ; extra == 'dev'
Requires-Dist: flake8-bugbear ; extra == 'dev'
Requires-Dist: flake8-isort ; extra == 'dev'
Requires-Dist: nox ; extra == 'dev'
